README.md
setup.cfg
setup.py
TMSRepair/TMSRepair_UIs.py
TMSRepair/TMSRepair_class.py
TMSRepair/TMSRepair_misc.py
TMSRepair/__init__.py
TMSRepair.egg-info/PKG-INFO
TMSRepair.egg-info/SOURCES.txt
TMSRepair.egg-info/dependency_links.txt
TMSRepair.egg-info/requires.txt
TMSRepair.egg-info/top_level.txt