Metadata-Version: 2.1
Name: TMSRepair
Version: 0.0.10
Summary: MNE extension for repairing TMS-evoked artifacts in EEG data
Home-page: https://github.com/marakw/TMSRepair.git
Author: Mara Wolter
Author-email: mara.k.wolter@gmail.com
License: MIT
Download-URL: https://github.com/marakw/TMSRepair.git
Platform: UNKNOWN
Classifier: Development Status :: 4 - Beta
Classifier: Environment :: Console
Classifier: Intended Audience :: Science/Research
Classifier: Programming Language :: Python :: 3
Classifier: Topic :: Scientific/Engineering :: Bio-Informatics
